README.md
setup.py
wpathr/__init__.py
wpathr/__main__.py
wpathr/wpathr.py
wpathr.egg-info/PKG-INFO
wpathr.egg-info/SOURCES.txt
wpathr.egg-info/dependency_links.txt
wpathr.egg-info/entry_points.txt
wpathr.egg-info/requires.txt
wpathr.egg-info/top_level.txt