Metadata-Version: 1.0
Name: wpathr
Version: 0.5.0
Summary: Path optimization tool and command runner for Windows
Home-page: https://github.com/vivainio/wpathr
Author: Ville Vainio
Author-email: vivainio@gmail.com
License: UNKNOWN
Platform: UNKNOWN
